.gitignore
LICENSE
MANIFEST.in
README.md
requirements-doc.txt
requirements.txt
setup.py
bpmodels/__init__.py
bpmodels.egg-info/PKG-INFO
bpmodels.egg-info/SOURCES.txt
bpmodels.egg-info/dependency_links.txt
bpmodels.egg-info/requires.txt
bpmodels.egg-info/top_level.txt
bpmodels/learning_rules/BCM.py
bpmodels/learning_rules/Oja.py
bpmodels/learning_rules/STDP.py
bpmodels/learning_rules/__init__.py
bpmodels/neurons/AdExIF_model.py
bpmodels/neurons/AdQuaIF_model.py
bpmodels/neurons/ExpIF_model.py
bpmodels/neurons/GeneralizedIF_model.py
bpmodels/neurons/HH_model.py
bpmodels/neurons/HindmarshRose_model.py
bpmodels/neurons/Izhikevich_model.py
bpmodels/neurons/LIF_model.py
bpmodels/neurons/MorrisLecar_model.py
bpmodels/neurons/QuaIF_model.py
bpmodels/neurons/ResonateandFire_model.py
bpmodels/neurons/WilsonCowan_model.py
bpmodels/neurons/__init__.py
bpmodels/synapses/AMPA.py
bpmodels/synapses/GABAa.py
bpmodels/synapses/GABAb.py
bpmodels/synapses/NMDA.py
bpmodels/synapses/STP.py
bpmodels/synapses/__init__.py
bpmodels/synapses/alpha.py
bpmodels/synapses/exponential.py
bpmodels/synapses/gap_junction.py
bpmodels/synapses/two_exponentials.py
bpmodels/synapses/voltage_jump.py