Metadata-Version: 2.1
Name: bpmodels
Version: 0.2.3
Summary: BrainPy-Models: An example package accompany with BrainPy.
Home-page: https://github.com/PKU-NIP-Lab/BrainPy-Models
Author: Pku-Nip-Lab
Author-email: adaduo@outlook.com
License: UNKNOWN
Keywords: computational neuroscience
Platform: UNKNOWN
Classifier: Intended Audience :: Science/Research
Classifier: Natural Language :: English
Classifier: Operating System :: OS Independent
Classifier: Programming Language :: Python
Classifier: Programming Language :: Python :: 3
Classifier: Topic :: Scientific/Engineering :: Bio-Informatics
Requires-Python: >=3.7
